Metadata-Version: 2.1
Name: kbarcz-hello
Version: 1.0.1
Summary: Hello world
Home-page: UNKNOWN
License: UNKNOWN
Platform: UNKNOWN
